Metadata-Version: 2.1
Name: hw-wwj
Version: 1.3.0
Summary: 测试fortran编写的程序在python中调用
Home-page: https://github.com/pypa/sampleproject
Author: banshiliuli
Author-email: 446601097@qq.com
License: UNKNOWN
Platform: UNKNOWN
Requires-Python: >=3.6
License-File: LICENSE.txt
